{"data":{"markdownRemark":{"html":"<h4>Polyalphabetic Cryptosystem</h4>\n<ul>\n<li>Affine cipher is a monoalphabetic cryptosystem</li>\n<li>\n<p>In polyaphabetic cipher</p>\n<ul>\n<li>More than one alphabets are used to encrypt the plaintext.</li>\n<li>The main pupose is to defeat frequency analysis attack</li>\n</ul>\n</li>\n</ul>\n<h4>Vigenere cipher</h4>\n<p><img src=\"./images/vigenere_cipher/Vigenere_cipher.JPG\" alt=\"alt text\" title=\"Vigenere_cipher\"></p>\n<h4>Exercise</h4>\n<p><img src=\"./images/vigenere_cipher/exercise.JPG\" alt=\"alt text\" title=\"Vigenere_cipher\"></p>\n<h4>More vigenere cipher</h4>\n<p><img src=\"./images/vigenere_cipher/vigenere_cipher_info.JPG\" alt=\"alt text\" title=\"Vigenere_cipher\"></p>\n<h4>Encryption function</h4>\n<p><img src=\"./images/vigenere_cipher/encryption.JPG\" alt=\"alt text\" title=\"Vigenere_cipher\"></p>\n<h4>Decryption</h4>\n<p><img src=\"./images/vigenere_cipher/decryption.JPG\" alt=\"alt text\" title=\"Vigenere_cipher\"></p>\n<h4>Cryptoanalysis of Vigenere cipher</h4>\n<ul>\n<li>\n<p>Frequency analysis:</p>\n<ul>\n<li>if you know the length of the keyword is n, you can break the ciphertext into n cosets and attack the cipher using frequency analysis if the ciphertext sample is long enough</li>\n</ul>\n</li>\n<li>\n<p>Friedman Test</p>\n<ul>\n<li>Find the incidence of Coincidence to determine wether or not a polyalphabetic substition has been used</li>\n<li>It is the probability that two randomly selected letters are the same</li>\n</ul>\n</li>\n<li>\n<p>Kasiski.</p>\n<ul>\n<li>Uses the occasional aligning of groups of letters with keyword to determine the length of the keyword.</li>\n</ul>\n</li>\n</ul>","frontmatter":{"title":""}}},"pageContext":{"slug":"/expr/cryptography/Vigenere_cipher/"}}